mpiprof/__init__.py
mpiprof/__main__.py
mpiprof/profiler.py
mpiprof-0.2.2.dist-info/METADATA
mpiprof-0.2.2.dist-info/WHEEL
mpiprof-0.2.2.dist-info/top_level.txt
mpiprof-0.2.2.dist-info/RECORD
