Metadata-Version: 2.4
Name: mpiprof
Version: 0.2.2
Summary: Profiler for MPI python programs
Author: Your Name
License: MIT
Project-URL: Homepage, https://github.com/JohannesBuchner/mpiprof.py
Project-URL: Repository, https://github.com/JohannesBuchner/mpiprof.py
Keywords: MPI,profiling,cProfile,mpi4py
Requires-Python: >=3.8
Requires-Dist: mpi4py>=3.1
